LICENSE
README.md
setup.py
.github/workflows/python-package-conda.yml
.github/workflows/python-publish.yml
examples/CompareFuzzyIntervalStochastic.py
examples/DampEstimateUncertaintyComparison.py
examples/HockettSherby.ipynb
examples/HockettSherby.py
examples/HockettSherbyInt.py
examples/HockettSherbyTikz.py
examples/IntervalAnalysis.ipynb
examples/IntervalAnalysis.py
examples/IntervalFn.ipynb
examples/IntervalFn.py
examples/PrintIntervalNumbers.py
examples/RosenbrockSens.py
examples/Sensitivities.py
examples/UncertainEigenfrequency.ipynb
examples/UncertainEigenfrequency.py
examples/UncertainEigenfrequency2dof.py
figures/Logo_pyUngewiss.svg
figures/pyUngewiss.png
pyUngewiss/OptAlgOptions.py
pyUngewiss/UncertainAnalysis.py
pyUngewiss/UncertainNumber.py
pyUngewiss/__init__.py
pyUngewiss.egg-info/PKG-INFO
pyUngewiss.egg-info/SOURCES.txt
pyUngewiss.egg-info/dependency_links.txt
pyUngewiss.egg-info/top_level.txt
test/test.py