Metadata-Version: 2.1
Name: pyUngewiss
Version: 1.1
Summary: Python library for UNcertainty analysis in liGhtwEight dsiGn with IntervalS and fuzzy numberS
Home-page: UNKNOWN
Author: E. J. Wehrle
Author-email: Erich.Wehrle@unibz.it
License: GPL3
Platform: UNKNOWN
License-File: LICENSE
